<?xml version="1.0" encoding="UTF-8"?>
<!--Generated by python, Author: Mengze.-->
<osm>
    <node concave_ob="0" dyn_ob="0" id="160021" lat="39.82449147" lon="116.18473904" smoke="0" type="-1" vel="4.2" water="0">
        <tag k="highway" v="traffic_signals"/>
    </node>
    <node concave_ob="0" dyn_ob="0" id="220001" lat="39.82450183" lon="116.18476411" smoke="0" type="-1" vel="4.2" water="0"/>
    <node concave_ob="0" dyn_ob="0" id="220002" lat="39.82450959" lon="116.18479038" smoke="0" type="-1" vel="4.2" water="0"/>
    <node concave_ob="0" dyn_ob="0" id="220003" lat="39.82451882" lon="116.18484751" smoke="0" type="-1" vel="8.4" water="0"/>
    <node concave_ob="0" dyn_ob="0" id="220004" lat="39.82452955" lon="116.18493579" smoke="0" type="-1" vel="8.4" water="0"/>
    <node concave_ob="0" dyn_ob="0" id="220005" lat="39.82453412" lon="116.18496288" smoke="0" type="-1" vel="4.2" water="0"/>
    <node concave_ob="0" dyn_ob="0" id="220006" lat="39.82454355" lon="116.18502416" smoke="0" type="-1" vel="4.2" water="0"/>
    <node concave_ob="0" dyn_ob="0" id="170018" lat="39.82454808" lon="116.18506124" smoke="0" type="-1" vel="4.2" water="0">
        <tag k="highway" v="traffic_signals"/>
    </node>
    <way id="220000">
        <nd ref="160021"/>
        <nd ref="220001"/>
        <nd ref="220002"/>
        <nd ref="220003"/>
        <nd ref="220004"/>
        <nd ref="220005"/>
        <nd ref="220006"/>
        <nd ref="170018"/>
        <tag k="name:en" v="double way"/>
    </way>
</osm>
